{
    "samples": [
        {
            "input": "",
            "reason": "t",
            "tag": "InvalidInput"
        },
        {
            "signatures": {
                "multiSignature": [
                    "94a125815a6dced4f37f4394b40e245c893a1c39b52f9363924696dc57e18f64d1fd7af3caa2ae17c6c57f0b8ee8d6749bb3f256d991958446160e9114f2e90d",
                    "80f8803eb2c4be2828fb4c6fa33d253507ba672732fa92c8081627737fd699855f6a3a8b38f475970861a186ffca1357c078828a14925fabd17b45b799d4b408",
                    "7f61aef9b0e16b353cc77d92fe30569809f16bebb5f06f78e538fd4d6be5512c52cdbae07d6b78a9ec7d334759bbecbfd53ef6a8e6a2c6c9e3a96bde93b98705",
                    "bbfb0c387837185ff6ac17db8f895099014d683a156d51609fcddc96791529b2cb7d4dd84d285ba5bf1207826360ac8df59398dfb2d4ae780558853b18789700",
                    "3bdc4b6cc99ce80996e906d066f233b28d765e991f647e0824a14a51ebe30b4490ae880e80db2315b33be1377216c8b4df966f65f87060e2c967a6ec50cfa405"
                ]
            },
            "snapshot": {
                "confirmedTransactions": [
                    {
                        "id": 0,
                        "inputs": [
                            -4,
                            -2,
                            0,
                            5
                        ],
                        "outputs": [
                            -4,
                            -2,
                            0,
                            3
                        ]
                    },
                    {
                        "id": 2,
                        "inputs": [],
                        "outputs": [
                            -6,
                            -5,
                            -1,
                            3,
                            4
                        ]
                    }
                ],
                "snapshotNumber": 4,
                "utxo": [
                    -4,
                    -2,
                    0,
                    3,
                    4
                ]
            },
            "tag": "SnapshotConfirmed"
        },
        {
            "tag": "TxInvalid",
            "transaction": {
                "id": 3,
                "inputs": [
                    -4,
                    5
                ],
                "outputs": [
                    -3,
                    -1,
                    1
                ]
            },
            "utxo": [
                -6,
                -4,
                5,
                6
            ],
            "validationError": {
                "reason": "T\\>F\t"
            }
        },
        {
            "tag": "HeadIsAborted",
            "utxo": [
                -5,
                2,
                6
            ]
        },
        {
            "tag": "TxSeen",
            "transaction": {
                "id": 0,
                "inputs": [
                    -5,
                    -4,
                    -1
                ],
                "outputs": []
            }
        },
        {
            "signatures": {
                "multiSignature": [
                    "194813e70f36a4623072c8c503b0c027f7f28cce1de73a60b72aa8037340c07719ac75705658f003aa2b96b6914d339a745736622826542402e698689cf0f402"
                ]
            },
            "snapshot": {
                "confirmedTransactions": [
                    {
                        "id": 1,
                        "inputs": [
                            -5,
                            2,
                            5
                        ],
                        "outputs": [
                            -3,
                            0,
                            6
                        ]
                    },
                    {
                        "id": 4,
                        "inputs": [
                            -6,
                            -2,
                            4
                        ],
                        "outputs": []
                    },
                    {
                        "id": 3,
                        "inputs": [],
                        "outputs": [
                            3
                        ]
                    }
                ],
                "snapshotNumber": 3,
                "utxo": []
            },
            "tag": "SnapshotConfirmed"
        },
        {
            "tag": "HeadIsOpen",
            "utxo": [
                -5,
                3
            ]
        },
        {
            "tag": "CommandFailed"
        },
        {
            "peer": {
                "hostname": "0.0.0.0",
                "port": 1
            },
            "tag": "PeerConnected"
        },
        {
            "signatures": {
                "multiSignature": []
            },
            "snapshot": {
                "confirmedTransactions": [
                    {
                        "id": -5,
                        "inputs": [
                            -5,
                            -3,
                            1
                        ],
                        "outputs": []
                    },
                    {
                        "id": 5,
                        "inputs": [
                            0
                        ],
                        "outputs": [
                            -2,
                            -1
                        ]
                    },
                    {
                        "id": 3,
                        "inputs": [
                            -6,
                            -3,
                            6
                        ],
                        "outputs": []
                    },
                    {
                        "id": 4,
                        "inputs": [
                            0,
                            2,
                            3
                        ],
                        "outputs": [
                            -3,
                            0,
                            5,
                            6
                        ]
                    },
                    {
                        "id": -1,
                        "inputs": [
                            -5,
                            0,
                            1,
                            3,
                            5,
                            6
                        ],
                        "outputs": [
                            -3,
                            3,
                            4
                        ]
                    }
                ],
                "snapshotNumber": 3,
                "utxo": [
                    -6,
                    2,
                    3,
                    5
                ]
            },
            "tag": "SnapshotConfirmed"
        },
        {
            "peer": {
                "hostname": "0.0.0.1",
                "port": 0
            },
            "tag": "PeerConnected"
        },
        {
            "party": {
                "vkey": "5ab80c0ff412d01ca6121febc210b8a79cb8b2a54fb169979ccc7e3d387db2ac"
            },
            "tag": "Committed",
            "utxo": [
                2
            ]
        },
        {
            "signatures": {
                "multiSignature": [
                    "1b9da904f12708363c88d4b96b33b474b2a5a863e290be2be5d4cacef8a5cbac1c0132c3e20e477d7affd1491be6577e8b83af012773beaf51c6df3f4af95b0e"
                ]
            },
            "snapshot": {
                "confirmedTransactions": [
                    {
                        "id": 4,
                        "inputs": [
                            -6,
                            -3,
                            1,
                            3
                        ],
                        "outputs": [
                            -5,
                            -1,
                            1,
                            6
                        ]
                    },
                    {
                        "id": -6,
                        "inputs": [
                            -6,
                            -5,
                            -2,
                            2,
                            4
                        ],
                        "outputs": [
                            -6,
                            1
                        ]
                    },
                    {
                        "id": -3,
                        "inputs": [
                            -5,
                            -4,
                            -3,
                            1,
                            4,
                            6
                        ],
                        "outputs": [
                            -4,
                            1,
                            5
                        ]
                    },
                    {
                        "id": -2,
                        "inputs": [],
                        "outputs": [
                            2,
                            6
                        ]
                    },
                    {
                        "id": -2,
                        "inputs": [
                            -6,
                            -3,
                            -2,
                            2,
                            3,
                            4
                        ],
                        "outputs": [
                            0,
                            2,
                            5
                        ]
                    },
                    {
                        "id": 2,
                        "inputs": [
                            -6,
                            -3,
                            5
                        ],
                        "outputs": []
                    }
                ],
                "snapshotNumber": 5,
                "utxo": [
                    4
                ]
            },
            "tag": "SnapshotConfirmed"
        },
        {
            "tag": "RolledBack"
        },
        {
            "tag": "HeadIsFinalized",
            "utxo": [
                -5,
                -2,
                1,
                2
            ]
        },
        {
            "peer": {
                "hostname": "0.0.0.5",
                "port": 6
            },
            "tag": "PeerConnected"
        },
        {
            "party": {
                "vkey": "3cab074cb1d6fdcd7789ba2f5fa4a12e78209b15ecb9181b011831e8b6010d49"
            },
            "tag": "Committed",
            "utxo": [
                0,
                2,
                4,
                5
            ]
        },
        {
            "tag": "RolledBack"
        },
        {
            "tag": "TxInvalid",
            "transaction": {
                "id": 3,
                "inputs": [
                    -5
                ],
                "outputs": [
                    -4,
                    -1,
                    0,
                    3,
                    6
                ]
            },
            "utxo": [],
            "validationError": {
                "reason": "ô†½¥\u001d\u001fj9!"
            }
        },
        {
            "tag": "HeadIsOpen",
            "utxo": [
                -4,
                1,
                5
            ]
        },
        {
            "tag": "CommandFailed"
        },
        {
            "tag": "RolledBack"
        },
        {
            "tag": "RolledBack"
        },
        {
            "tag": "RolledBack"
        },
        {
            "tag": "GetUTxOResponse",
            "utxo": [
                -6,
                -3,
                -2,
                -1,
                0,
                2
            ]
        },
        {
            "me": {
                "vkey": "3b6a27bcceb6a42d62a3a8d02a6f0d73653215771de243a63ac048a18b59da29"
            },
            "tag": "Greetings"
        },
        {
            "party": {
                "vkey": "3b6a27bcceb6a42d62a3a8d02a6f0d73653215771de243a63ac048a18b59da29"
            },
            "tag": "Committed",
            "utxo": [
                -6,
                -5,
                -4,
                0,
                2,
                4
            ]
        },
        {
            "peer": {
                "hostname": "0.0.0.0",
                "port": 4
            },
            "tag": "PeerConnected"
        },
        {
            "tag": "TxValid",
            "transaction": {
                "id": 4,
                "inputs": [
                    -6,
                    -5,
                    -2,
                    3
                ],
                "outputs": [
                    -6,
                    -1,
                    0,
                    4,
                    5,
                    6
                ]
            }
        },
        {
            "tag": "HeadIsFinalized",
            "utxo": [
                -4
            ]
        },
        {
            "tag": "HeadIsOpen",
            "utxo": [
                -6,
                -5,
                -3,
                -2,
                3
            ]
        },
        {
            "tag": "TxSeen",
            "transaction": {
                "id": -6,
                "inputs": [
                    4
                ],
                "outputs": [
                    -4,
                    -3,
                    1
                ]
            }
        },
        {
            "peer": {
                "hostname": "0.0.0.0",
                "port": 6
            },
            "tag": "PeerDisconnected"
        },
        {
            "snapshot": {
                "confirmedTransactions": [
                    {
                        "id": -2,
                        "inputs": [
                            -3,
                            -2
                        ],
                        "outputs": [
                            -5,
                            0,
                            4
                        ]
                    },
                    {
                        "id": 6,
                        "inputs": [
                            1,
                            3
                        ],
                        "outputs": [
                            -6,
                            0,
                            4,
                            5
                        ]
                    }
                ],
                "snapshotNumber": 6,
                "utxo": [
                    -2,
                    4
                ]
            },
            "tag": "HeadIsClosed"
        },
        {
            "snapshot": {
                "confirmedTransactions": [],
                "snapshotNumber": 4,
                "utxo": [
                    -6,
                    -2,
                    0,
                    2,
                    3,
                    5
                ]
            },
            "tag": "HeadIsClosed"
        },
        {
            "input": "U",
            "reason": "Mj",
            "tag": "InvalidInput"
        },
        {
            "party": {
                "vkey": "b0a0d1a0eaac73d68d1a8f7af72751627d70884e1d483a601538c340f2dec557"
            },
            "tag": "Committed",
            "utxo": [
                -6,
                -3,
                0,
                1
            ]
        },
        {
            "tag": "TxInvalid",
            "transaction": {
                "id": 2,
                "inputs": [
                    -5,
                    -2,
                    1,
                    2
                ],
                "outputs": [
                    -6
                ]
            },
            "utxo": [
                -5,
                -4,
                -3,
                -1,
                2
            ],
            "validationError": {
                "reason": "?&"
            }
        },
        {
            "tag": "TxSeen",
            "transaction": {
                "id": -2,
                "inputs": [
                    -6,
                    -5,
                    0,
                    3
                ],
                "outputs": [
                    -6,
                    -4
                ]
            }
        },
        {
            "tag": "CommandFailed"
        },
        {
            "me": {
                "vkey": "36460356b489b175a3cb77f747143dfa4d1d44858fdecbd1426f75fc0025628a"
            },
            "tag": "Greetings"
        },
        {
            "tag": "RolledBack"
        },
        {
            "tag": "RolledBack"
        },
        {
            "tag": "HeadIsAborted",
            "utxo": [
                4
            ]
        },
        {
            "peer": {
                "hostname": "0.0.0.3",
                "port": 5
            },
            "tag": "PeerConnected"
        },
        {
            "input": "\u0014ðŸ›§",
            "reason": "ð«¦Œôˆ¢³\r9N",
            "tag": "InvalidInput"
        },
        {
            "tag": "CommandFailed"
        },
        {
            "parties": [
                {
                    "vkey": "d186c06afa703e01615ac564c8a66c8b70f177bfe4a283b8969818ce684286b2"
                }
            ],
            "tag": "ReadyToCommit"
        },
        {
            "tag": "TxInvalid",
            "transaction": {
                "id": -1,
                "inputs": [
                    -1,
                    0,
                    2
                ],
                "outputs": [
                    -5,
                    6
                ]
            },
            "utxo": [
                -3,
                0,
                3,
                4,
                5
            ],
            "validationError": {
                "reason": "\n56"
            }
        },
        {
            "tag": "TxValid",
            "transaction": {
                "id": 6,
                "inputs": [],
                "outputs": [
                    -5,
                    -3,
                    6
                ]
            }
        },
        {
            "input": "E",
            "reason": "1[",
            "tag": "InvalidInput"
        },
        {
            "tag": "HeadIsFinalized",
            "utxo": [
                0,
                2,
                6
            ]
        },
        {
            "peer": {
                "hostname": "0.0.0.8",
                "port": 4
            },
            "tag": "PeerConnected"
        },
        {
            "tag": "RolledBack"
        },
        {
            "tag": "HeadIsAborted",
            "utxo": [
                -3,
                0,
                5
            ]
        },
        {
            "tag": "HeadIsAborted",
            "utxo": [
                -4,
                -1,
                5
            ]
        },
        {
            "input": "cqôƒº¯",
            "reason": ";+?\\î¢¥b",
            "tag": "InvalidInput"
        },
        {
            "tag": "HeadIsOpen",
            "utxo": [
                -5,
                -4,
                4
            ]
        },
        {
            "tag": "TxSeen",
            "transaction": {
                "id": 6,
                "inputs": [
                    -5,
                    -4,
                    -1,
                    1,
                    2,
                    4
                ],
                "outputs": []
            }
        },
        {
            "peer": {
                "hostname": "0.0.0.8",
                "port": 7
            },
            "tag": "PeerDisconnected"
        },
        {
            "tag": "HeadIsOpen",
            "utxo": [
                0,
                1
            ]
        },
        {
            "input": "\"\u0005bô–3",
            "reason": "ó½¸ \u0011\"\u0017D9",
            "tag": "InvalidInput"
        },
        {
            "peer": {
                "hostname": "0.0.0.1",
                "port": 2
            },
            "tag": "PeerConnected"
        },
        {
            "tag": "HeadIsOpen",
            "utxo": [
                0,
                2,
                4
            ]
        },
        {
            "input": "ð£¿•\u0005\u000e;ó°|",
            "reason": "ô‹†¡ð¬€°ô‡·®ó¼ª",
            "tag": "InvalidInput"
        },
        {
            "snapshot": {
                "confirmedTransactions": [
                    {
                        "id": -4,
                        "inputs": [
                            -3,
                            5
                        ],
                        "outputs": [
                            -5,
                            3,
                            6
                        ]
                    },
                    {
                        "id": -3,
                        "inputs": [
                            0,
                            5,
                            6
                        ],
                        "outputs": [
                            -6,
                            -2,
                            1,
                            3
                        ]
                    },
                    {
                        "id": -6,
                        "inputs": [
                            3,
                            4
                        ],
                        "outputs": [
                            0,
                            4
                        ]
                    },
                    {
                        "id": -5,
                        "inputs": [
                            -1,
                            2,
                            3
                        ],
                        "outputs": [
                            -5,
                            -4,
                            -2,
                            1,
                            3
                        ]
                    },
                    {
                        "id": 1,
                        "inputs": [
                            4
                        ],
                        "outputs": [
                            0,
                            2
                        ]
                    }
                ],
                "snapshotNumber": 2,
                "utxo": [
                    -4,
                    6
                ]
            },
            "tag": "HeadIsClosed"
        },
        {
            "peer": {
                "hostname": "0.0.0.2",
                "port": 0
            },
            "tag": "PeerConnected"
        },
        {
            "tag": "HeadIsOpen",
            "utxo": [
                -5,
                -4,
                -3,
                3,
                4
            ]
        },
        {
            "tag": "GetUTxOResponse",
            "utxo": [
                5
            ]
        },
        {
            "parties": [
                {
                    "vkey": "63337563fdadcd4ad36a81c2ec2d507bbe2562bcf8a231f548cd11f992d27c55"
                },
                {
                    "vkey": "edbb9649ab2923bb90ba3fa68414f5860540e485c4ded7ae388021cd56f3f29f"
                },
                {
                    "vkey": "9be3287795907809407e14439ff198d5bfc7dce6f9bc743cb369146f610b4801"
                }
            ],
            "tag": "ReadyToCommit"
        },
        {
            "input": "\u001cul_8",
            "reason": "",
            "tag": "InvalidInput"
        },
        {
            "tag": "HeadIsFinalized",
            "utxo": [
                -4,
                -3,
                -2,
                0,
                6
            ]
        },
        {
            "peer": {
                "hostname": "0.0.0.4",
                "port": 4
            },
            "tag": "PeerConnected"
        },
        {
            "tag": "RolledBack"
        },
        {
            "postChainTx": {
                "confirmedSnapshot": {
                    "signatures": {
                        "multiSignature": []
                    },
                    "snapshot": {
                        "confirmedTransactions": [
                            {
                                "id": 0,
                                "inputs": [
                                    -5,
                                    -4,
                                    -3,
                                    -2,
                                    5
                                ],
                                "outputs": [
                                    -5,
                                    -3,
                                    0
                                ]
                            },
                            {
                                "id": 1,
                                "inputs": [
                                    -6,
                                    -2,
                                    -1
                                ],
                                "outputs": []
                            },
                            {
                                "id": -4,
                                "inputs": [
                                    -6,
                                    1,
                                    4
                                ],
                                "outputs": []
                            }
                        ],
                        "snapshotNumber": 2,
                        "utxo": [
                            -4,
                            1,
                            6
                        ]
                    },
                    "tag": "ConfirmedSnapshot"
                },
                "tag": "CloseTx"
            },
            "postTxError": {
                "tag": "MoreThanOneUTxOCommitted"
            },
            "tag": "PostTxOnChainFailed"
        },
        {
            "tag": "HeadIsAborted",
            "utxo": [
                -5,
                -3,
                -1,
                2,
                4
            ]
        },
        {
            "tag": "TxInvalid",
            "transaction": {
                "id": -4,
                "inputs": [
                    4
                ],
                "outputs": [
                    -2,
                    3,
                    6
                ]
            },
            "utxo": [
                -6,
                -5,
                1,
                4
            ],
            "validationError": {
                "reason": "ð®ž )"
            }
        },
        {
            "peer": {
                "hostname": "0.0.0.8",
                "port": 1
            },
            "tag": "PeerConnected"
        },
        {
            "me": {
                "vkey": "fc9862419b52cd3874b6be15a77c74bfac84c29fbb60b8836e021e3a77fc20f4"
            },
            "tag": "Greetings"
        },
        {
            "tag": "HeadIsFinalized",
            "utxo": [
                -1,
                1,
                5
            ]
        },
        {
            "tag": "HeadIsOpen",
            "utxo": [
                5
            ]
        },
        {
            "signatures": {
                "multiSignature": [
                    "f7d1aadd4ba78f5a83e89d2029a5f251f078d428712868a61e5a68b435f9372f0c997a6df50ba831c4809c6c2c5433f0ebda9d3880f9f4675761727fcf5cab0b",
                    "f5e4f585b7a1d3b8a6694437427b72eb82d4cf6b5cab498e712b4416a4fe0b5fe61256ba3cf0c2a0c8cfec935af33f1da38fc1ac0147c68edd70efbd0798620f"
                ]
            },
            "snapshot": {
                "confirmedTransactions": [
                    {
                        "id": 5,
                        "inputs": [
                            -4,
                            1,
                            5
                        ],
                        "outputs": [
                            -2,
                            -1,
                            2,
                            6
                        ]
                    },
                    {
                        "id": 5,
                        "inputs": [
                            -4,
                            -1,
                            1,
                            4
                        ],
                        "outputs": []
                    },
                    {
                        "id": 1,
                        "inputs": [
                            -4,
                            3,
                            5
                        ],
                        "outputs": [
                            -3,
                            -2,
                            5
                        ]
                    },
                    {
                        "id": 3,
                        "inputs": [],
                        "outputs": [
                            -2,
                            -1,
                            1,
                            6
                        ]
                    }
                ],
                "snapshotNumber": 1,
                "utxo": [
                    -1,
                    0,
                    3,
                    4,
                    5,
                    6
                ]
            },
            "tag": "SnapshotConfirmed"
        },
        {
            "tag": "TxSeen",
            "transaction": {
                "id": -5,
                "inputs": [
                    4
                ],
                "outputs": [
                    -6,
                    -5,
                    -2,
                    0,
                    6
                ]
            }
        },
        {
            "tag": "HeadIsFinalized",
            "utxo": [
                -1
            ]
        },
        {
            "input": "\u0003ð ±¡",
            "reason": "\u001b\u001e\u0006",
            "tag": "InvalidInput"
        },
        {
            "me": {
                "vkey": "8bd366aa4db8d525631f94ab54886afbb90060ec614967364133c79a4e7eff75"
            },
            "tag": "Greetings"
        },
        {
            "me": {
                "vkey": "c39c6746c6ea1f948a44ca7cc57206150a92d9a904817c01f756ca631bc65acf"
            },
            "tag": "Greetings"
        },
        {
            "tag": "RolledBack"
        },
        {
            "tag": "TxSeen",
            "transaction": {
                "id": 6,
                "inputs": [
                    -3
                ],
                "outputs": [
                    -6,
                    -3,
                    -1,
                    2,
                    5
                ]
            }
        },
        {
            "tag": "HeadIsOpen",
            "utxo": [
                -2
            ]
        },
        {
            "tag": "HeadIsAborted",
            "utxo": [
                -2
            ]
        },
        {
            "tag": "RolledBack"
        },
        {
            "tag": "HeadIsFinalized",
            "utxo": [
                -6,
                -5,
                1,
                6
            ]
        },
        {
            "snapshot": {
                "confirmedTransactions": [
                    {
                        "id": -6,
                        "inputs": [
                            -5,
                            3
                        ],
                        "outputs": [
                            0
                        ]
                    },
                    {
                        "id": -4,
                        "inputs": [],
                        "outputs": [
                            -6,
                            -4,
                            6
                        ]
                    },
                    {
                        "id": 5,
                        "inputs": [
                            -2,
                            4
                        ],
                        "outputs": [
                            -6,
                            -3,
                            -2,
                            0
                        ]
                    },
                    {
                        "id": 0,
                        "inputs": [],
                        "outputs": [
                            -4,
                            1
                        ]
                    }
                ],
                "snapshotNumber": 4,
                "utxo": [
                    -2,
                    6
                ]
            },
            "tag": "HeadIsClosed"
        },
        {
            "party": {
                "vkey": "b1ba92cec4fd16fd4c13d6489744c27b1d73acc7255b02e2fe8638386f7d2fa2"
            },
            "tag": "Committed",
            "utxo": [
                -5,
                -4,
                4
            ]
        },
        {
            "party": {
                "vkey": "2a071c6dcbe051e8eacfd2e295ac1a799b9235409a51445b33e51e67e3f34aee"
            },
            "tag": "Committed",
            "utxo": [
                0,
                3,
                5
            ]
        },
        {
            "me": {
                "vkey": "cce2455c8e370478e071d34fd9ef6598836b8a10836ae9f5d73ce7600cda61cf"
            },
            "tag": "Greetings"
        },
        {
            "tag": "HeadIsFinalized",
            "utxo": [
                0,
                3
            ]
        },
        {
            "tag": "CommandFailed"
        },
        {
            "tag": "TxSeen",
            "transaction": {
                "id": 0,
                "inputs": [
                    -3,
                    -2,
                    5
                ],
                "outputs": [
                    -6,
                    1
                ]
            }
        },
        {
            "party": {
                "vkey": "6c1a36e607fda50013069fee8ae2e32144431ce92a5e7e8e67bc1eb85be65c13"
            },
            "tag": "Committed",
            "utxo": [
                -4,
                -3,
                0,
                1,
                6
            ]
        },
        {
            "input": "ð¡‹…>!",
            "reason": "r\u0008",
            "tag": "InvalidInput"
        },
        {
            "signatures": {
                "multiSignature": []
            },
            "snapshot": {
                "confirmedTransactions": [
                    {
                        "id": 4,
                        "inputs": [
                            -5,
                            6
                        ],
                        "outputs": [
                            -6,
                            0,
                            3,
                            6
                        ]
                    }
                ],
                "snapshotNumber": 1,
                "utxo": [
                    -4
                ]
            },
            "tag": "SnapshotConfirmed"
        },
        {
            "peer": {
                "hostname": "0.0.0.6",
                "port": 4
            },
            "tag": "PeerConnected"
        },
        {
            "tag": "CommandFailed"
        },
        {
            "peer": {
                "hostname": "0.0.0.6",
                "port": 8
            },
            "tag": "PeerConnected"
        },
        {
            "snapshot": {
                "confirmedTransactions": [
                    {
                        "id": 5,
                        "inputs": [],
                        "outputs": [
                            -6,
                            -1,
                            1,
                            3,
                            5,
                            6
                        ]
                    },
                    {
                        "id": 3,
                        "inputs": [
                            -1,
                            1,
                            2,
                            5
                        ],
                        "outputs": [
                            2,
                            3
                        ]
                    },
                    {
                        "id": 2,
                        "inputs": [
                            -5,
                            -4,
                            -3,
                            -1
                        ],
                        "outputs": [
                            0,
                            1,
                            2,
                            3,
                            5
                        ]
                    },
                    {
                        "id": 5,
                        "inputs": [
                            5
                        ],
                        "outputs": []
                    }
                ],
                "snapshotNumber": 3,
                "utxo": [
                    -2,
                    -1,
                    0
                ]
            },
            "tag": "HeadIsClosed"
        },
        {
            "tag": "RolledBack"
        },
        {
            "tag": "HeadIsAborted",
            "utxo": [
                -1
            ]
        },
        {
            "parties": [
                {
                    "vkey": "655a9f9546221972d4495186aa89e6ddf4d2680556b1349c539e4e5aa85eded0"
                },
                {
                    "vkey": "3b6a27bcceb6a42d62a3a8d02a6f0d73653215771de243a63ac048a18b59da29"
                },
                {
                    "vkey": "815879427727efd8428e15f8b98ba7f98ea2c8457381a293a96065c86ca48416"
                }
            ],
            "tag": "ReadyToCommit"
        },
        {
            "input": "\u0000có½½¼_",
            "reason": "b6DGì½Œ",
            "tag": "InvalidInput"
        },
        {
            "tag": "GetUTxOResponse",
            "utxo": [
                5
            ]
        },
        {
            "tag": "HeadIsOpen",
            "utxo": [
                -6,
                -5,
                5
            ]
        },
        {
            "tag": "CommandFailed"
        },
        {
            "input": "ð ‚·KE",
            "reason": "\u001cé®¤",
            "tag": "InvalidInput"
        },
        {
            "tag": "HeadIsAborted",
            "utxo": [
                -2,
                5
            ]
        },
        {
            "tag": "RolledBack"
        },
        {
            "me": {
                "vkey": "b895557d324d4a4acdf7344240ad987bdc7550a394ac0de85bebeb315c1a7a60"
            },
            "tag": "Greetings"
        },
        {
            "tag": "GetUTxOResponse",
            "utxo": [
                2
            ]
        },
        {
            "input": "l",
            "reason": "c",
            "tag": "InvalidInput"
        },
        {
            "postChainTx": {
                "tag": "FanoutTx",
                "utxo": [
                    -3,
                    -2,
                    -1,
                    6
                ]
            },
            "postTxError": {
                "tag": "NoSeedInput"
            },
            "tag": "PostTxOnChainFailed"
        },
        {
            "signatures": {
                "multiSignature": [
                    "a8f1c7a7185e66875d7fd2c2c62e861dfa42f1100c935324283887ff137330d54c98f457cc4f1b083f627f2bf3efcbfdb4cb807a221d869272c2d8904839b001",
                    "6233b68a7119cd113f48f93a79ead185d2ee89ba8ab96f96887a5e574d304028c0575ee2f8a59b2131282241ec3be7aae6bb1332c24364f5c2d733869a4cbc03",
                    "a383d6ebb3340aa5e1ef886c88eb25024cf347f2e67a7f39368f8edd7d6fd0fb333cb001ae59248ce0e3ca7e9ca84f39ff60fa18f7e862f89886c18d8115790c"
                ]
            },
            "snapshot": {
                "confirmedTransactions": [
                    {
                        "id": -4,
                        "inputs": [],
                        "outputs": [
                            -3,
                            -1,
                            0,
                            2
                        ]
                    },
                    {
                        "id": 0,
                        "inputs": [
                            -6,
                            -2,
                            0
                        ],
                        "outputs": [
                            0,
                            1,
                            3,
                            4,
                            6
                        ]
                    },
                    {
                        "id": 0,
                        "inputs": [
                            -6,
                            -5,
                            1,
                            2,
                            3,
                            6
                        ],
                        "outputs": [
                            -3,
                            -2,
                            1,
                            6
                        ]
                    },
                    {
                        "id": 5,
                        "inputs": [],
                        "outputs": [
                            -4,
                            -1,
                            0,
                            1,
                            3
                        ]
                    }
                ],
                "snapshotNumber": 2,
                "utxo": [
                    3,
                    5
                ]
            },
            "tag": "SnapshotConfirmed"
        },
        {
            "tag": "CommandFailed"
        },
        {
            "snapshot": {
                "confirmedTransactions": [
                    {
                        "id": 3,
                        "inputs": [
                            -3,
                            -2,
                            1,
                            4
                        ],
                        "outputs": [
                            -1,
                            6
                        ]
                    },
                    {
                        "id": -6,
                        "inputs": [],
                        "outputs": [
                            5
                        ]
                    },
                    {
                        "id": -5,
                        "inputs": [
                            -6,
                            -5,
                            -3,
                            -2,
                            2
                        ],
                        "outputs": [
                            -3,
                            -1,
                            2,
                            5
                        ]
                    },
                    {
                        "id": 3,
                        "inputs": [
                            -6,
                            1,
                            6
                        ],
                        "outputs": [
                            3
                        ]
                    }
                ],
                "snapshotNumber": 5,
                "utxo": [
                    -4,
                    -1,
                    1,
                    2
                ]
            },
            "tag": "HeadIsClosed"
        },
        {
            "snapshot": {
                "confirmedTransactions": [],
                "snapshotNumber": 4,
                "utxo": [
                    4
                ]
            },
            "tag": "HeadIsClosed"
        },
        {
            "tag": "TxInvalid",
            "transaction": {
                "id": 4,
                "inputs": [],
                "outputs": [
                    -3,
                    -1,
                    6
                ]
            },
            "utxo": [
                -4,
                -2,
                1
            ],
            "validationError": {
                "reason": "ô‡§ "
            }
        },
        {
            "tag": "TxValid",
            "transaction": {
                "id": 0,
                "inputs": [
                    -3,
                    -1,
                    2,
                    3,
                    5
                ],
                "outputs": [
                    -6,
                    -3,
                    1,
                    5
                ]
            }
        },
        {
            "tag": "TxSeen",
            "transaction": {
                "id": -1,
                "inputs": [
                    -1,
                    6
                ],
                "outputs": [
                    5
                ]
            }
        },
        {
            "peer": {
                "hostname": "0.0.0.6",
                "port": 1
            },
            "tag": "PeerDisconnected"
        },
        {
            "tag": "TxSeen",
            "transaction": {
                "id": 6,
                "inputs": [
                    -2,
                    -1,
                    0,
                    1,
                    5
                ],
                "outputs": [
                    -4
                ]
            }
        },
        {
            "peer": {
                "hostname": "0.0.0.8",
                "port": 2
            },
            "tag": "PeerConnected"
        },
        {
            "input": "N1",
            "reason": ":r,!S",
            "tag": "InvalidInput"
        },
        {
            "peer": {
                "hostname": "0.0.0.2",
                "port": 0
            },
            "tag": "PeerDisconnected"
        },
        {
            "tag": "TxInvalid",
            "transaction": {
                "id": 4,
                "inputs": [
                    -1,
                    1,
                    2
                ],
                "outputs": [
                    -2,
                    0,
                    4,
                    6
                ]
            },
            "utxo": [
                -6,
                -4,
                -3,
                2,
                4
            ],
            "validationError": {
                "reason": "5zó³Ž”\u001eô‡Œ©"
            }
        },
        {
            "input": "^d6",
            "reason": ",G/uXð©¼ˆ",
            "tag": "InvalidInput"
        },
        {
            "party": {
                "vkey": "232071a8fb2887405b99c3678d79cbb099aa90df69757842489677e747fac3c4"
            },
            "tag": "Committed",
            "utxo": [
                -3,
                6
            ]
        },
        {
            "tag": "HeadIsFinalized",
            "utxo": [
                3,
                4,
                6
            ]
        },
        {
            "tag": "HeadIsFinalized",
            "utxo": [
                -5,
                -3,
                -2,
                3
            ]
        },
        {
            "me": {
                "vkey": "93eaa1b7c17ef820dc59057f1e869986678e013bcf95818d6d9f2c0cd22cda16"
            },
            "tag": "Greetings"
        },
        {
            "tag": "RolledBack"
        },
        {
            "peer": {
                "hostname": "0.0.0.7",
                "port": 2
            },
            "tag": "PeerDisconnected"
        },
        {
            "tag": "GetUTxOResponse",
            "utxo": [
                -2,
                0,
                5
            ]
        },
        {
            "tag": "GetUTxOResponse",
            "utxo": [
                -6,
                -5,
                -4,
                0
            ]
        },
        {
            "snapshot": {
                "confirmedTransactions": [
                    {
                        "id": -3,
                        "inputs": [
                            -3,
                            0,
                            3,
                            6
                        ],
                        "outputs": [
                            -4,
                            -1
                        ]
                    },
                    {
                        "id": 2,
                        "inputs": [
                            1,
                            2
                        ],
                        "outputs": [
                            -5
                        ]
                    },
                    {
                        "id": -1,
                        "inputs": [],
                        "outputs": [
                            -1,
                            0,
                            4,
                            5,
                            6
                        ]
                    },
                    {
                        "id": -5,
                        "inputs": [
                            -6,
                            2
                        ],
                        "outputs": [
                            -3,
                            -2,
                            0,
                            1
                        ]
                    },
                    {
                        "id": -1,
                        "inputs": [
                            -2,
                            2
                        ],
                        "outputs": [
                            3,
                            5
                        ]
                    }
                ],
                "snapshotNumber": 1,
                "utxo": []
            },
            "tag": "HeadIsClosed"
        },
        {
            "party": {
                "vkey": "9ad6572a2275e27b6fda185ae4d86f75d9ce38aa5f89b44c13d03bb7b5cb38f7"
            },
            "tag": "Committed",
            "utxo": [
                -6,
                1,
                2,
                5
            ]
        },
        {
            "postChainTx": {
                "confirmedSnapshot": {
                    "snapshot": {
                        "confirmedTransactions": [
                            {
                                "id": -6,
                                "inputs": [
                                    -6,
                                    -4,
                                    -3,
                                    6
                                ],
                                "outputs": [
                                    -1,
                                    0,
                                    4
                                ]
                            },
                            {
                                "id": -6,
                                "inputs": [
                                    -6,
                                    -5,
                                    -4,
                                    -3,
                                    2
                                ],
                                "outputs": [
                                    -4,
                                    4
                                ]
                            },
                            {
                                "id": -4,
                                "inputs": [
                                    0
                                ],
                                "outputs": []
                            },
                            {
                                "id": 2,
                                "inputs": [
                                    -5
                                ],
                                "outputs": [
                                    -1,
                                    2,
                                    4
                                ]
                            },
                            {
                                "id": -6,
                                "inputs": [
                                    -5,
                                    -3,
                                    2,
                                    5
                                ],
                                "outputs": [
                                    -6,
                                    -5,
                                    -1,
                                    5
                                ]
                            },
                            {
                                "id": 4,
                                "inputs": [
                                    -6,
                                    -5,
                                    -1,
                                    3
                                ],
                                "outputs": [
                                    -1,
                                    0,
                                    4
                                ]
                            }
                        ],
                        "snapshotNumber": 0,
                        "utxo": [
                            -6,
                            -5,
                            -2,
                            0,
                            2,
                            3
                        ]
                    },
                    "tag": "InitialSnapshot"
                },
                "tag": "CloseTx"
            },
            "postTxError": {
                "knownUTxO": [
                    -2,
                    4
                ],
                "tag": "CannotFindOwnInitial"
            },
            "tag": "PostTxOnChainFailed"
        },
        {
            "tag": "GetUTxOResponse",
            "utxo": [
                -3,
                1
            ]
        },
        {
            "tag": "TxValid",
            "transaction": {
                "id": 5,
                "inputs": [],
                "outputs": [
                    -6,
                    -5,
                    0,
                    4
                ]
            }
        },
        {
            "tag": "TxValid",
            "transaction": {
                "id": 2,
                "inputs": [
                    -2,
                    0,
                    1,
                    3,
                    5
                ],
                "outputs": [
                    -3,
                    -1,
                    1,
                    2,
                    6
                ]
            }
        },
        {
            "party": {
                "vkey": "5183bcf2fd1853a2fca98abf805fd7c72441ed2405253aece7eca6a040733e35"
            },
            "tag": "Committed",
            "utxo": [
                -4,
                -3,
                -1,
                5
            ]
        },
        {
            "party": {
                "vkey": "9977d43492f7abdd7398fe44c5d3e72c8474fbd53b8fc5b3a8e4a1d412af8200"
            },
            "tag": "Committed",
            "utxo": []
        },
        {
            "signatures": {
                "multiSignature": [
                    "37adbb2dd993ab4d82c14167fcfaa70d068bd2722a43145120587f25c627ecabeb4d67783faf7c22678f7d3d9479f0111f8947173acf5ea2a274cc7177e65105",
                    "153375bfd8083a0203d3ed8b2f0d2d2b6be5528144e65bb14f7b7785fc9c0a60cbd9219de21e77c6d2648be5337e000d835c8aac250dac05742a64f1b6e95a08"
                ]
            },
            "snapshot": {
                "confirmedTransactions": [
                    {
                        "id": 6,
                        "inputs": [
                            -6,
                            -1,
                            5
                        ],
                        "outputs": [
                            -6,
                            -3,
                            3
                        ]
                    },
                    {
                        "id": -5,
                        "inputs": [
                            -5,
                            -3,
                            -2,
                            5
                        ],
                        "outputs": []
                    },
                    {
                        "id": -2,
                        "inputs": [
                            -5,
                            -1,
                            5,
                            6
                        ],
                        "outputs": [
                            -4,
                            -3,
                            -1,
                            0
                        ]
                    },
                    {
                        "id": -4,
                        "inputs": [
                            -3,
                            2,
                            5
                        ],
                        "outputs": [
                            3,
                            4
                        ]
                    }
                ],
                "snapshotNumber": 2,
                "utxo": [
                    -4,
                    1,
                    3,
                    4,
                    5
                ]
            },
            "tag": "SnapshotConfirmed"
        },
        {
            "tag": "RolledBack"
        },
        {
            "snapshot": {
                "confirmedTransactions": [
                    {
                        "id": -2,
                        "inputs": [
                            -3,
                            -2
                        ],
                        "outputs": [
                            5
                        ]
                    }
                ],
                "snapshotNumber": 4,
                "utxo": [
                    2
                ]
            },
            "tag": "HeadIsClosed"
        },
        {
            "postChainTx": {
                "snapshot": {
                    "confirmedTransactions": [
                        {
                            "id": 2,
                            "inputs": [
                                -6,
                                1
                            ],
                            "outputs": []
                        }
                    ],
                    "snapshotNumber": 5,
                    "utxo": [
                        4
                    ]
                },
                "tag": "ContestTx"
            },
            "postTxError": {
                "knownUTxO": [
                    -2,
                    -1,
                    2,
                    3,
                    5
                ],
                "tag": "CannotFindOwnInitial"
            },
            "tag": "PostTxOnChainFailed"
        },
        {
            "parties": [],
            "tag": "ReadyToCommit"
        },
        {
            "tag": "HeadIsOpen",
            "utxo": []
        },
        {
            "peer": {
                "hostname": "0.0.0.6",
                "port": 0
            },
            "tag": "PeerDisconnected"
        },
        {
            "peer": {
                "hostname": "0.0.0.4",
                "port": 6
            },
            "tag": "PeerConnected"
        },
        {
            "tag": "HeadIsAborted",
            "utxo": [
                2
            ]
        },
        {
            "tag": "RolledBack"
        },
        {
            "tag": "TxValid",
            "transaction": {
                "id": -5,
                "inputs": [
                    -5,
                    -3,
                    1,
                    3,
                    6
                ],
                "outputs": [
                    -6,
                    -3,
                    4,
                    6
                ]
            }
        },
        {
            "tag": "HeadIsFinalized",
            "utxo": [
                -1,
                0,
                1,
                3,
                5
            ]
        },
        {
            "snapshot": {
                "confirmedTransactions": [],
                "snapshotNumber": 0,
                "utxo": [
                    -4,
                    0,
                    5,
                    6
                ]
            },
            "tag": "HeadIsClosed"
        },
        {
            "snapshot": {
                "confirmedTransactions": [
                    {
                        "id": 3,
                        "inputs": [
                            0,
                            3,
                            5
                        ],
                        "outputs": []
                    },
                    {
                        "id": 0,
                        "inputs": [
                            -6,
                            0,
                            2,
                            3
                        ],
                        "outputs": [
                            -2,
                            1,
                            6
                        ]
                    },
                    {
                        "id": 0,
                        "inputs": [],
                        "outputs": [
                            -4,
                            2,
                            5,
                            6
                        ]
                    },
                    {
                        "id": 2,
                        "inputs": [
                            1,
                            3
                        ],
                        "outputs": [
                            -4,
                            0,
                            4
                        ]
                    }
                ],
                "snapshotNumber": 3,
                "utxo": [
                    -4,
                    -3,
                    1,
                    5
                ]
            },
            "tag": "HeadIsClosed"
        },
        {
            "tag": "TxValid",
            "transaction": {
                "id": 1,
                "inputs": [
                    -6,
                    4,
                    6
                ],
                "outputs": [
                    3,
                    6
                ]
            }
        },
        {
            "tag": "RolledBack"
        },
        {
            "postChainTx": {
                "committed": [
                    -6,
                    -5,
                    1,
                    4,
                    5
                ],
                "party": {
                    "vkey": "4171ff85faaf080b53a45521d00b90a82e133b6d82cc7bfbde58e1ba316d6368"
                },
                "tag": "CommitTx"
            },
            "postTxError": {
                "headUTxO": [
                    -5,
                    -4,
                    -1,
                    0
                ],
                "input": "H",
                "tag": "CannotSpendInput",
                "walletUTxO": [
                    5
                ]
            },
            "tag": "PostTxOnChainFailed"
        },
        {
            "tag": "HeadIsAborted",
            "utxo": [
                -6,
                -5,
                -4,
                1
            ]
        },
        {
            "tag": "HeadIsOpen",
            "utxo": [
                -4,
                -3,
                -2,
                0,
                4
            ]
        },
        {
            "tag": "GetUTxOResponse",
            "utxo": [
                -6,
                -3,
                -1,
                1
            ]
        },
        {
            "tag": "TxValid",
            "transaction": {
                "id": 5,
                "inputs": [
                    -1,
                    3,
                    4,
                    5
                ],
                "outputs": [
                    -6,
                    -5,
                    -3,
                    -1,
                    3
                ]
            }
        },
        {
            "input": "é†·Z\u0012\u0002-\u0010",
            "reason": "*ó¸¯³ðªžˆe| ",
            "tag": "InvalidInput"
        },
        {
            "tag": "HeadIsOpen",
            "utxo": [
                -2,
                5
            ]
        },
        {
            "snapshot": {
                "confirmedTransactions": [],
                "snapshotNumber": 4,
                "utxo": [
                    -6,
                    0,
                    1,
                    2,
                    5
                ]
            },
            "tag": "HeadIsClosed"
        },
        {
            "tag": "TxSeen",
            "transaction": {
                "id": -2,
                "inputs": [],
                "outputs": [
                    -4,
                    -1,
                    0,
                    4
                ]
            }
        },
        {
            "party": {
                "vkey": "e620407c3b8c3a3d5bbcf4c5c6c3b2023abe78043180b17a57f00bf0b3255a24"
            },
            "tag": "Committed",
            "utxo": []
        },
        {
            "postChainTx": {
                "snapshot": {
                    "confirmedTransactions": [
                        {
                            "id": 4,
                            "inputs": [
                                5
                            ],
                            "outputs": [
                                0,
                                4
                            ]
                        },
                        {
                            "id": -5,
                            "inputs": [
                                2,
                                6
                            ],
                            "outputs": [
                                1
                            ]
                        },
                        {
                            "id": -2,
                            "inputs": [
                                -2,
                                2,
                                4,
                                5,
                                6
                            ],
                            "outputs": [
                                -6,
                                1,
                                2,
                                3
                            ]
                        },
                        {
                            "id": 2,
                            "inputs": [
                                -5,
                                5
                            ],
                            "outputs": [
                                -6,
                                0,
                                1,
                                5,
                                6
                            ]
                        }
                    ],
                    "snapshotNumber": 3,
                    "utxo": [
                        2,
                        5,
                        6
                    ]
                },
                "tag": "ContestTx"
            },
            "postTxError": {
                "failureReason": "",
                "tag": "FailedToPostTx"
            },
            "tag": "PostTxOnChainFailed"
        },
        {
            "peer": {
                "hostname": "0.0.0.0",
                "port": 8
            },
            "tag": "PeerConnected"
        },
        {
            "tag": "RolledBack"
        },
        {
            "tag": "HeadIsOpen",
            "utxo": [
                -6,
                -5,
                0
            ]
        },
        {
            "tag": "TxInvalid",
            "transaction": {
                "id": -4,
                "inputs": [
                    -6,
                    -2,
                    5,
                    6
                ],
                "outputs": []
            },
            "utxo": [
                -3,
                0,
                2,
                3
            ],
            "validationError": {
                "reason": "1"
            }
        },
        {
            "tag": "RolledBack"
        },
        {
            "tag": "TxValid",
            "transaction": {
                "id": 4,
                "inputs": [
                    2
                ],
                "outputs": [
                    -3,
                    -1,
                    2
                ]
            }
        },
        {
            "postChainTx": {
                "headParameters": {
                    "contestationPeriod": -2.604411301e-2,
                    "parties": [
                        {
                            "vkey": "3be533822b146a67b7649397f6fdcde0451233eda282997fe31c4dcc0a9b09fb"
                        }
                    ]
                },
                "tag": "InitTx"
            },
            "postTxError": {
                "tag": "MoreThanOneUTxOCommitted"
            },
            "tag": "PostTxOnChainFailed"
        },
        {
            "me": {
                "vkey": "a9713a351d0b99a808cd2cc3442dfd056dc125542a4db433069df9eeaa56c0c7"
            },
            "tag": "Greetings"
        },
        {
            "peer": {
                "hostname": "0.0.0.7",
                "port": 4
            },
            "tag": "PeerDisconnected"
        },
        {
            "tag": "CommandFailed"
        },
        {
            "tag": "TxValid",
            "transaction": {
                "id": -1,
                "inputs": [
                    -2,
                    -1,
                    2,
                    5
                ],
                "outputs": [
                    -4,
                    3
                ]
            }
        },
        {
            "party": {
                "vkey": "7fd4447c76783cc45d766ff081445f37b455b8e898325dc72142f4ba0662c153"
            },
            "tag": "Committed",
            "utxo": []
        },
        {
            "me": {
                "vkey": "42a41c4ec4f3d750e04c70b21d8d38a8b1d80ed1f6bcbd20a3f0d41c4818d9ea"
            },
            "tag": "Greetings"
        },
        {
            "tag": "CommandFailed"
        },
        {
            "signatures": {
                "multiSignature": [
                    "618efe9fa6eff27e44cf958c668aba34947605b658081bb7f0bfafcf3479a7e3b1fc5010071829a7eb0edf6d21c605d00602cf4a6b89c81140faee6a07efd500",
                    "b736babc602ff386e29e43936d4414db6f4929476fff3fa618c32bb5116a23b78391b5ab31ff01ebd312713e4dd20829284ca8ebd1abce0511ceecb79fe98c07"
                ]
            },
            "snapshot": {
                "confirmedTransactions": [
                    {
                        "id": -5,
                        "inputs": [
                            1
                        ],
                        "outputs": [
                            -5,
                            -4,
                            0,
                            2,
                            4
                        ]
                    },
                    {
                        "id": -5,
                        "inputs": [
                            -5,
                            -2,
                            -1,
                            1,
                            3
                        ],
                        "outputs": [
                            -5,
                            5
                        ]
                    },
                    {
                        "id": -5,
                        "inputs": [
                            -1,
                            1,
                            4,
                            5
                        ],
                        "outputs": [
                            -5,
                            -3,
                            -1,
                            0,
                            2
                        ]
                    },
                    {
                        "id": 2,
                        "inputs": [],
                        "outputs": [
                            -2,
                            -1,
                            4
                        ]
                    },
                    {
                        "id": 4,
                        "inputs": [
                            -5,
                            -3,
                            -2,
                            0,
                            4
                        ],
                        "outputs": [
                            -5,
                            -3,
                            0,
                            1,
                            6
                        ]
                    },
                    {
                        "id": 0,
                        "inputs": [
                            -1,
                            3,
                            4,
                            5
                        ],
                        "outputs": [
                            -6,
                            -2,
                            2
                        ]
                    }
                ],
                "snapshotNumber": 0,
                "utxo": [
                    -6,
                    -4,
                    3,
                    5,
                    6
                ]
            },
            "tag": "SnapshotConfirmed"
        },
        {
            "tag": "HeadIsFinalized",
            "utxo": []
        },
        {
            "input": "\u0002P",
            "reason": "Wdð¡¹…YT/",
            "tag": "InvalidInput"
        },
        {
            "signatures": {
                "multiSignature": []
            },
            "snapshot": {
                "confirmedTransactions": [
                    {
                        "id": 4,
                        "inputs": [
                            -5,
                            -4,
                            -2,
                            1
                        ],
                        "outputs": []
                    },
                    {
                        "id": -4,
                        "inputs": [
                            -5,
                            -3,
                            0,
                            4
                        ],
                        "outputs": [
                            -2,
                            -1,
                            4,
                            5
                        ]
                    },
                    {
                        "id": 0,
                        "inputs": [],
                        "outputs": [
                            -6,
                            2,
                            3,
                            4
                        ]
                    },
                    {
                        "id": 5,
                        "inputs": [
                            -3,
                            1,
                            2,
                            3,
                            6
                        ],
                        "outputs": [
                            -4,
                            -1,
                            0,
                            3,
                            6
                        ]
                    }
                ],
                "snapshotNumber": 0,
                "utxo": [
                    -1,
                    1,
                    4,
                    5
                ]
            },
            "tag": "SnapshotConfirmed"
        },
        {
            "tag": "HeadIsOpen",
            "utxo": [
                -6,
                -2,
                3,
                4
            ]
        },
        {
            "tag": "HeadIsAborted",
            "utxo": [
                2
            ]
        },
        {
            "tag": "CommandFailed"
        },
        {
            "peer": {
                "hostname": "0.0.0.5",
                "port": 7
            },
            "tag": "PeerConnected"
        }
    ],
    "seed": -2075412563
}